archive_hocr_tools-1.1.22.data/scripts/abbyy-to-hocr
archive_hocr_tools-1.1.22.data/scripts/fts-text-annotate
archive_hocr_tools-1.1.22.data/scripts/fts-text-match
archive_hocr_tools-1.1.22.data/scripts/hocr-combine-stream
archive_hocr_tools-1.1.22.data/scripts/hocr-extract-page
archive_hocr_tools-1.1.22.data/scripts/hocr-fold-chars
archive_hocr_tools-1.1.22.data/scripts/hocr-lookup-check
archive_hocr_tools-1.1.22.data/scripts/hocr-lookup-create
archive_hocr_tools-1.1.22.data/scripts/hocr-lookup-reconstruct
archive_hocr_tools-1.1.22.data/scripts/hocr-split-pages
archive_hocr_tools-1.1.22.data/scripts/hocr-text
archive_hocr_tools-1.1.22.data/scripts/hocr-text-paragraphs
archive_hocr_tools-1.1.22.data/scripts/hocr-to-epub
archive_hocr_tools-1.1.22.data/scripts/pdf-to-hocr
hocr/__init__.py
hocr/fts.py
hocr/parse.py
hocr/searching.py
hocr/text.py
hocr/util.py
hocr/version.py
hocr/data/abbyy-lang-map.csv
archive_hocr_tools-1.1.22.dist-info/COPYING
archive_hocr_tools-1.1.22.dist-info/LICENSE.txt
archive_hocr_tools-1.1.22.dist-info/METADATA
archive_hocr_tools-1.1.22.dist-info/WHEEL
archive_hocr_tools-1.1.22.dist-info/top_level.txt
archive_hocr_tools-1.1.22.dist-info/RECORD
